coppercomm/config_file_parser.py
coppercomm/device.py
coppercomm/device_factory.py
coppercomm/fastboot_interface.py
coppercomm/device_adb/__init__.py
coppercomm/device_adb/adb_interface.py
coppercomm/device_common/exceptions.py
coppercomm/device_common/interfaces.py
coppercomm/device_common/local_console.py
coppercomm/device_serial/__init__.py
coppercomm/device_serial/console.py
coppercomm/device_serial/device_serial.py
coppercomm/device_serial/serial_console_interface.py
coppercomm/device_state_monitor/__init__.py
coppercomm/loggers/__init__.py
coppercomm/loggers/device_logger.py
coppercomm/loggers/device_logging.json
coppercomm/loggers/serial_logger.py
coppercomm/loggers/adb_logger/__init__.py
coppercomm/loggers/adb_logger/adb_logger.py
coppercomm/loggers/adb_logger/adb_logger_thread.py
coppercomm/loggers/pytest_fixtures/__init__.py
coppercomm/loggers/pytest_fixtures/log_fixtures.py
coppercomm/loggers/utils/__init__.py
coppercomm/loggers/utils/log_dir.py
coppercomm/pytest_fixtures/device_fixtures.py
coppercomm/pytest_fixtures/dryrun/__init__.py
coppercomm/ssh_connection/__init__.py
coppercomm/ssh_connection/ssh_connection.py
coppercomm-0.1.0.dist-info/METADATA
coppercomm-0.1.0.dist-info/WHEEL
coppercomm-0.1.0.dist-info/licenses/LICENSE
coppercomm-0.1.0.dist-info/licenses/NOTICE
coppercomm-0.1.0.dist-info/RECORD
