Metadata-Version: 2.3
Name: coppercomm
Version: 0.1.0
Summary: Coppercomm
Project-URL: Homepage, https://github.com/volvo-cars/coppercomm
Project-URL: Issues, https://github.com/volvo-cars/coppercomm/issues
Author: Volvo Cars
License: Apache License
License-File: LICENSE
License-File: NOTICE
Requires-Python: >=3.8
Requires-Dist: paramiko
Requires-Dist: pexpect
Requires-Dist: pyserial
